judge0_client/__init__.py
judge0_client/client.py
judge0_client/models/__init__.py
judge0_client/models/about_response.py
judge0_client/models/base_response_model.py
judge0_client/models/base_submission.py
judge0_client/models/multi_file_submission.py
judge0_client/models/single_file_submission.py
judge0_client/models/submission_detail.py
judge0_client/models/submission_response.py
judge0_client/models/submission_status.py
judge0_client/models/workers_response.py
judge0_client/py.typed
judge0_client/types.py
judge0_client/utils/__init__.py
judge0_client/utils/base64_utils.py
judge0_client/utils/exceptions.py
judge0_client/utils/zip_utils.py
judge0_client-0.3.1.dist-info/WHEEL
judge0_client-0.3.1.dist-info/METADATA
judge0_client-0.3.1.dist-info/RECORD
