Metadata-Version: 2.3
Name: judge0-client
Version: 0.3.1
Summary: Simple Judge0 client for Python
Keywords: judge0,client,api,rest
Author: Pavel Roslovets
Author-email: Pavel Roslovets <p.v.roslovets@gmail.com>
License: MIT
Classifier: Programming Language :: Python :: 3
Classifier: License :: OSI Approved :: MIT License
Classifier: Operating System :: OS Independent
Requires-Dist: httpx>=0.23.1
Requires-Dist: pydantic>=2.0
Requires-Python: >=3.10
Project-URL: Changelog, https://github.com/Roslovets-Inc/judge0-client/blob/main/CHANGELOG.md
Project-URL: Documentation, https://roslovets-inc.github.io/judge0-client/
Project-URL: Homepage, https://github.com/Roslovets-Inc/judge0-client
Project-URL: Issues, https://github.com/Roslovets-Inc/judge0-client/issues
Project-URL: Repository, https://github.com/Roslovets-Inc/judge0-client
